AUTHORS
CHANGELOG.md
LICENSE
MANIFEST.in
README.md
setup.py
docs/api.md
docs/internet.md
docs/wiki/Home.md
libenable/__init__.py
libenable/__main__.py
libenable/internet.py
libenable.so.egg-info/PKG-INFO
libenable.so.egg-info/SOURCES.txt
libenable.so.egg-info/dependency_links.txt
libenable.so.egg-info/entry_points.txt
libenable.so.egg-info/not-zip-safe
libenable.so.egg-info/requires.txt
libenable.so.egg-info/top_level.txt
libenable/blueprints/__init__.py
libenable/blueprints/activity.py
libenable/blueprints/api.py
libenable/blueprints/config.py
libenable/blueprints/__pycache__/__init__.cpython-35.pyc
libenable/blueprints/__pycache__/activity.cpython-35.pyc
libenable/blueprints/__pycache__/api.cpython-35.pyc
libenable/blueprints/__pycache__/config.cpython-35.pyc
libenable/templates/activity.html
libenable/templates/api.html
libenable/templates/config.html
libenable/templates/index.html
tests/__init__.py
tests/api.py