Metadata-Version: 1.1
Name: libenable.so
Version: 0.3.0
Summary: A Python module for enabling access to different protected domains
Home-page: https://bitbucket.org/bkvaluemeal/libenable.so
Author: Justin Willis
Author-email: sirJustin.Willis@gmail.com
License: ISC License
Keywords: captcha
Platform: UNKNOWN
Classifier: Development Status :: 4 - Beta
Classifier: Environment :: Web Environment
Classifier: Framework :: Flask
Classifier: Intended Audience :: Developers
Classifier: License :: OSI Approved :: ISC License (ISCL)
Classifier: Operating System :: Unix
Classifier: Programming Language :: Python :: 3
Classifier: Topic :: Other/Nonlisted Topic
